crashlink/__init__.py
crashlink/__main__.py
crashlink/asm.py
crashlink/core.py
crashlink/decomp.py
crashlink/disasm.py
crashlink/errors.py
crashlink/globals.py
crashlink/hlc.py
crashlink/opcodes.py
crashlink/pseudo.py
crashlink/py.typed
crashlink/interp/__init__.py
crashlink/interp/std.py
crashlink/interp/vm.py
crashlink-0.0.5.dist-info/licenses/LICENSE
crashtest/__init__.py
crashtest/__main__.py
crashtest/build.py
crashtest/models.py
crashtest/run.py
crashtest/templates/_result.html
crashtest/templates/index.html
hlrun/__init__.py
hlrun/core.py
hlrun/globals.py
hlrun/obj.py
hlrun/patch.py
crashlink-0.0.5.dist-info/METADATA
crashlink-0.0.5.dist-info/WHEEL
crashlink-0.0.5.dist-info/entry_points.txt
crashlink-0.0.5.dist-info/top_level.txt
crashlink-0.0.5.dist-info/RECORD
