Metadata-Version: 2.4
Name: crashlink
Version: 0.0.5
Summary: Just another HashLink decompiler/disassembler.
Author-email: N3rdL0rd <n3rdl0rd@proton.me>
License-Expression: MIT
Classifier: Programming Language :: Python :: 3
Classifier: Operating System :: OS Independent
Classifier: Topic :: Software Development :: Disassemblers
Classifier: Topic :: Software Development :: Libraries :: Python Modules
Classifier: Typing :: Typed
Requires-Python: >=3.10
License-File: LICENSE
Provides-Extra: dev
Requires-Dist: pdoc3; extra == "dev"
Requires-Dist: build; extra == "dev"
Requires-Dist: twine; extra == "dev"
Requires-Dist: mypy; extra == "dev"
Requires-Dist: radon; extra == "dev"
Requires-Dist: pytest; extra == "dev"
Requires-Dist: tqdm; extra == "dev"
Requires-Dist: snakeviz; extra == "dev"
Requires-Dist: typeguard; extra == "dev"
Requires-Dist: types-tqdm; extra == "dev"
Requires-Dist: dill; extra == "dev"
Requires-Dist: pytest-xdist; extra == "dev"
Requires-Dist: staticjinja; extra == "dev"
Requires-Dist: IPython; extra == "dev"
Requires-Dist: requests; extra == "dev"
Requires-Dist: ruff; extra == "dev"
Requires-Dist: pygments; extra == "dev"
Requires-Dist: types-Pygments; extra == "dev"
Requires-Dist: markupsafe; extra == "dev"
Provides-Extra: extras
Requires-Dist: tqdm; extra == "extras"
Requires-Dist: dill; extra == "extras"
Requires-Dist: IPython; extra == "extras"
Requires-Dist: pygments; extra == "extras"
Dynamic: license-file
